dotbot_neverland/__init__.py
dotbot_neverland/bot.py
dotbot_neverland/parsing.py
dotbot_neverland/models/__init__.py
dotbot_neverland/models/_base.py
dotbot_neverland/models/_filter_attrs.py
dotbot_neverland/models/events.py
dotbot_neverland/models/raw.py
dotbot_neverland/models/users.py
dotbot_neverland/utils/aliases.py
dotbot_neverland/utils/custom_id.py
dotbot_neverland/utils/parcing_utils.py
dotbot_neverland/utils/validators.py
dotbot_neverland-0.1.3.dist-info/METADATA
dotbot_neverland-0.1.3.dist-info/WHEEL
dotbot_neverland-0.1.3.dist-info/RECORD
