Metadata-Version: 2.3
Name: dotbot-neverland
Version: 0.1.3
Summary: Add your description here
Project-URL: Homepage, https://github.com/xjzh123/dotbot-neverland
Project-URL: Documentation, https://github.com/xjzh123/dotbot-neverland/tree/master/docs
Project-URL: Repository, https://github.com/xjzh123/dotbot-neverland.git
Author-email: xjzh123 <37945610+xjzh123@users.noreply.github.com>
Requires-Python: >=3.12
Requires-Dist: attrs>=23.2.0
Requires-Dist: websockets>=12.0
